{
  "lastCheck": "2025-08-31T12:05:00+02:00",
  "events": [
    { "ticker": "ET",   "date": "2025-08-28", "label": "Insider cluster buy (director repeat) — AVWAP hold monitor" },
    { "ticker": "GPRE", "date": "2025-08-28", "label": "Oppenheimer upgrade → Outperform (PT $14)" },
    { "ticker": "PSTG", "date": "2025-08-27", "label": "Beat & raise; Meta revenue recognized; multi-analyst upgrades" },
    { "ticker": "PSTG", "date": "2025-09-25", "label": "Investor event — Meta ramp commentary" },
    { "ticker": "TSM",  "date": "2025-08-28", "label": "Reports: early allocation of 2nm (N2) capacity to Apple; packaging capacity watch" },
    { "ticker": "BTC",  "date": "2025-08-29", "label": "Spot-ETF net inflow shift (trend watch)" },
    { "ticker": "ETH",  "date": "2025-08-29", "label": "Core-dev upgrade cadence; staking dynamics" },
    { "ticker": "SOL",  "date": "2025-08-29", "label": "Uptime sustained; ecosystem milestones" },
    { "ticker": "RNDR", "date": "2025-08-29", "label": "AI-compute network utilization pickup" },
    { "ticker": "ONDO", "date": "2025-08-29", "label": "RWA adoption uptick (tokenized treasuries flows)" },
    { "ticker": "WST",  "date": "2025-07-24", "label": "EPS beat + raised FY EPS; price confirm" },
    { "ticker": "PLTR", "date": "2025-08-20", "label": "Raised guidance + new gov contracts; price confirm" },
    { "ticker": "ASAN", "date": "2025-08-28", "label": "Insider cluster buys; breakout with >1.5× volume" },
    { "ticker": "NVS",  "date": "2025-07-17", "label": "EPS growth + margin expansion; approvals/readouts (moat)" },
    { "ticker": "VGT",  "date": "2025-08-29", "label": "Heartbeat outflow (~$3B) from ETF.com email" }
  ],
  "graduations": [
    {
      "ticker": "PSTG",
      "tier": "Tier 2 (3%)",
      "proof": "Beat & raise; GM expansion; Meta deployment confirmed; multi-upgrades; price confirm vs event-day AVWAP",
      "source": "Company ER + analyst notes",
      "date": "2025-08-28"
    },
    {
      "ticker": "ASAN",
      "tier": "Tier 3 (1.5%)",
      "proof": "Founder/insider buys; range-high breakout on >1.5× volume; close > event-day AVWAP",
      "source": "SEC Form 4 + tape",
      "date": "2025-08-28"
    },
    {
      "ticker": "NVS",
      "tier": "Tier 2 (3%)",
      "proof": "Core EPS growth; margin expansion; multiple approvals indicating moat",
      "source": "Company results + regulatory",
      "date": "2025-08-29"
    },
    {
      "ticker": "INTC",
      "tier": "Tier 2 (3–5%)",
      "proof": "EPS positive; net margin improvement; strategic US government stake (moat); price confirm",
      "source": "Major media + filings summary",
      "date": "2025-08-25"
    }
  ],
  "alerts": [
    {
      "date": "2025-08-29T13:20:00+02:00",
      "type": "flow",
      "label": "VGT ~−$3B heartbeat outflow; monitor 3–5 sessions"
    },
    {
      "date": "2025-08-30T10:22:00+02:00",
      "type": "macro-refresh",
      "label": "Catalysts.macro refreshed: next 10 days (Case-Shiller, Beige Book, ADP/Claims/ULC, NFP/UR/AHE)"
    }
  ]
}